{"이미지 정보":{"이미지 식별자":132007,"이미지 높이":800,"이미지 파일명":"Gru_521_01.jpg","이미지 너비":800},"데이터셋 정보":{"파일 생성일자":"2020-08-14 07:31:31","데이터셋 상세설명":{"렉트좌표":{"아우터":[{}],"하의":[{}],"원피스":[{"X좌표":231.203,"Y좌표":45.5,"가로":305,"세로":632}],"상의":[{}]},"폴리곤좌표":{"아우터":[{}],"하의":[{}],"원피스":[{"Y좌표9":462.0,"Y좌표22":58.0,"Y좌표21":254.0,"Y좌표23":53.0,"Y좌표20":281.0,"X좌표19":292.703,"X좌표18":259.703,"X좌표17":234.703,"X좌표16":265.703,"X좌표15":313.703,"X좌표14":351.703,"X좌표13":387.703,"X좌표12":443.703,"X좌표11":489.703,"Y좌표4":46.0,"X좌표10":516.703,"Y좌표3":85.0,"Y좌표2":81.0,"Y좌표1":49.0,"Y좌표8":395.0,"Y좌표7":266.0,"Y좌표6":198.0,"Y좌표5":61.0,"Y좌표15":678.0,"Y좌표14":678.0,"X좌표8":494.703,"Y좌표17":626.0,"X좌표9":488.703,"Y좌표16":665.0,"Y좌표11":677.0,"Y좌표10":675.0,"Y좌표13":662.0,"Y좌표12":661.0,"X좌표23":341.703,"X좌표22":298.703,"X좌표2":352.703,"X좌표21":231.703,"X좌표3":422.703,"X좌표20":300.703,"X좌표1":341.703,"X좌표6":536.703,"Y좌표19":398.0,"X좌표7":496.703,"Y좌표18":485.0,"X좌표4":447.703,"X좌표5":500.703}],"상의":[{}]},"라벨링":{"스타일":[{"스타일":"리조트","서브스타일":"로맨틱"}],"아우터":[{}],"하의":[{}],"원피스":[{"기장":"발목","색상":"화이트","카테고리":"드레스","디테일":["드롭숄더","프릴"],"소매기장":"7부소매","프린트":["무지"],"넥라인":"스퀘어넥","핏":"루즈"}],"상의":[{}]}},"파일 번호":132007,"파일 이름":"Gru_521_01.jpg"}}