{"이미지 정보":{"이미지 식별자":84290,"이미지 높이":800,"이미지 파일명":"KANOZO_012_06.jpg","이미지 너비":800},"데이터셋 정보":{"파일 생성일자":"2020-08-10 06:39:20","데이터셋 상세설명":{"렉트좌표":{"아우터":[{}],"하의":[{}],"원피스":[{"X좌표":158.5,"Y좌표":2.5,"가로":303,"세로":629}],"상의":[{}]},"폴리곤좌표":{"아우터":[{}],"하의":[{}],"원피스":[{"Y좌표9":336.0,"Y좌표20":466.0,"X좌표19":249.0,"X좌표18":208.0,"X좌표17":232.0,"X좌표16":257.0,"X좌표15":292.0,"X좌표14":324.0,"X좌표13":367.0,"X좌표12":395.0,"X좌표11":451.0,"Y좌표4":580.0,"X좌표10":461.0,"Y좌표3":585.0,"Y좌표2":566.0,"Y좌표1":478.0,"Y좌표8":376.0,"Y좌표7":529.0,"Y좌표6":632.0,"Y좌표5":607.0,"Y좌표15":13.0,"Y좌표14":29.0,"X좌표8":445.0,"Y좌표17":92.0,"X좌표9":462.0,"Y좌표16":29.0,"Y좌표11":30.0,"Y좌표10":56.0,"Y좌표13":31.0,"Y좌표12":3.0,"X좌표2":159.0,"X좌표3":260.0,"X좌표20":184.0,"X좌표1":181.0,"X좌표6":446.0,"Y좌표19":330.0,"X좌표7":457.0,"Y좌표18":309.0,"X좌표4":307.0,"X좌표5":311.0}],"상의":[{}]},"라벨링":{"스타일":[{"스타일":"리조트"}],"아우터":[{}],"하의":[{}],"원피스":[{"기장":"미디","색상":"블랙","서브색상":"와인","카테고리":"드레스","디테일":["셔링"],"소매기장":"긴팔","소재":["우븐"],"프린트":["체크","무지"],"넥라인":"라운드넥","핏":"루즈"}],"상의":[{}]}},"파일 번호":84290,"파일 이름":"KANOZO_012_06.jpg"}}