{"이미지 정보":{"이미지 식별자":101975,"이미지 높이":800,"이미지 파일명":"batch_GATE_026_02.jpg","이미지 너비":800},"데이터셋 정보":{"파일 생성일자":"2020-08-10 08:45:04","데이터셋 상세설명":{"렉트좌표":{"아우터":[{}],"하의":[{}],"원피스":[{}],"상의":[{"X좌표":186.5,"Y좌표":31.5156,"가로":431,"세로":615}]},"폴리곤좌표":{"아우터":[{}],"하의":[{}],"원피스":[{}],"상의":[{"X좌표33":193.0,"X좌표32":187.0,"X좌표31":191.0,"X좌표30":226.0,"X좌표8":487.0,"X좌표9":577.0,"Y좌표33":136.016,"Y좌표32":323.016,"Y좌표31":482.016,"Y좌표30":516.016,"X좌표2":230.0,"X좌표3":338.0,"X좌표1":193.0,"X좌표6":432.0,"X좌표7":461.0,"X좌표4":368.0,"X좌표5":402.0,"Y좌표26":583.016,"Y좌표25":573.016,"Y좌표28":447.016,"Y좌표9":62.0156,"Y좌표27":471.016,"Y좌표22":464.016,"Y좌표21":476.016,"Y좌표24":599.016,"Y좌표23":647.016,"Y좌표20":462.016,"X좌표19":561.0,"X좌표18":555.0,"X좌표17":583.0,"X좌표16":596.0,"X좌표15":618.0,"X좌표14":595.0,"X좌표13":608.0,"X좌표12":610.0,"X좌표11":592.0,"Y좌표4":93.0156,"X좌표10":581.0,"Y좌표3":38.0156,"Y좌표2":62.0156,"Y좌표1":133.016,"Y좌표8":53.0156,"Y좌표7":32.0156,"Y좌표29":481.016,"Y좌표6":109.016,"Y좌표5":192.016,"Y좌표15":381.016,"Y좌표14":363.016,"Y좌표17":411.016,"Y좌표16":433.016,"Y좌표11":134.016,"Y좌표10":87.0156,"Y좌표13":341.016,"Y좌표12":301.016,"X좌표29":310.0,"X좌표28":306.0,"X좌표27":355.0,"X좌표26":350.0,"X좌표25":377.0,"X좌표24":378.0,"X좌표23":445.0,"X좌표22":438.0,"X좌표21":478.0,"X좌표20":515.0,"Y좌표19":454.016,"Y좌표18":408.016}]},"라벨링":{"스타일":[{"스타일":"로맨틱"}],"아우터":[{}],"하의":[{}],"원피스":[{}],"상의":[{"색상":"핑크","서브색상":"그린","카테고리":"블라우스","디테일":["프릴","띠"],"소매기장":"7부소매","소재":["실크"],"프린트":["플로럴"],"핏":"루즈"}]}},"파일 번호":101975,"파일 이름":"batch_GATE_026_02.jpg"}}