{"이미지 정보":{"이미지 식별자":109575,"이미지 높이":800,"이미지 파일명":"girlis_884_06.jpg","이미지 너비":800},"데이터셋 정보":{"파일 생성일자":"2020-08-10 09:28:01","데이터셋 상세설명":{"렉트좌표":{"아우터":[{}],"하의":[{}],"원피스":[{}],"상의":[{"X좌표":187.246,"Y좌표":105.36,"가로":429,"세로":523}]},"폴리곤좌표":{"아우터":[{}],"하의":[{}],"원피스":[{}],"상의":[{"Y좌표9":623.14,"X좌표19":240.672,"X좌표18":196.733,"X좌표17":187.746,"X좌표16":220.7,"X좌표15":269.632,"X좌표14":282.614,"X좌표13":480.339,"X좌표12":517.287,"X좌표11":531.268,"Y좌표4":133.821,"X좌표10":557.232,"Y좌표3":106.858,"Y좌표2":105.86,"Y좌표1":129.826,"Y좌표8":588.189,"Y좌표7":556.233,"Y좌표6":422.419,"Y좌표5":191.74,"Y좌표15":628.133,"Y좌표14":605.165,"X좌표8":608.161,"Y좌표17":552.239,"X좌표9":606.164,"Y좌표16":629.132,"Y좌표11":591.185,"Y좌표10":627.135,"Y좌표13":610.158,"Y좌표12":608.161,"X좌표2":331.546,"X좌표3":478.342,"X좌표1":242.669,"X좌표6":598.175,"Y좌표19":132.822,"X좌표7":617.149,"Y좌표18":471.351,"X좌표4":563.224,"X좌표5":586.192}]},"라벨링":{"스타일":[{"스타일":"로맨틱","서브스타일":"페미닌"}],"아우터":[{}],"하의":[{}],"원피스":[{}],"상의":[{"색상":"화이트","카테고리":"블라우스","디테일":["단추","프릴"],"소매기장":"긴팔","넥라인":"라운드넥","핏":"노멀"}]}},"파일 번호":109575,"파일 이름":"girlis_884_06.jpg"}}