{"이미지 정보":{"이미지 식별자":107503,"이미지 높이":800,"이미지 파일명":"girlis_740_img.jpg","이미지 너비":800},"데이터셋 정보":{"파일 생성일자":"2020-08-10 09:16:06","데이터셋 상세설명":{"렉트좌표":{"아우터":[{}],"하의":[{}],"원피스":[{"X좌표":238.102,"Y좌표":143.975,"가로":332,"세로":577}],"상의":[{}]},"폴리곤좌표":{"아우터":[{}],"하의":[{}],"원피스":[{"X좌표8":306.408,"X좌표9":279.756,"X좌표2":256.93,"X좌표3":238.602,"X좌표1":337.016,"X좌표6":318.887,"X좌표7":318.887,"X좌표4":277.25,"X좌표5":298.965,"Y좌표26":150.958,"Y좌표25":155.11,"Y좌표9":567.097,"Y좌표22":247.842,"Y좌표21":282.905,"Y좌표24":157.417,"Y좌표23":223.852,"Y좌표20":336.883,"X좌표19":480.496,"X좌표18":492.783,"X좌표17":512.819,"X좌표16":521.892,"X좌표15":526.429,"X좌표14":531.532,"X좌표13":443.637,"X좌표12":374.834,"X좌표11":270.305,"Y좌표4":262.146,"X좌표10":265.012,"Y좌표3":206.714,"Y좌표2":183.375,"Y좌표1":144.475,"Y좌표8":453.605,"Y좌표7":430.385,"Y좌표6":381.275,"Y좌표5":320.009,"Y좌표15":595.24,"Y좌표14":713.807,"Y좌표17":473.443,"Y좌표16":586.474,"Y좌표11":707.81,"Y좌표10":661.674,"Y좌표13":716.575,"Y좌표12":721.65,"X좌표26":352.907,"X좌표25":458.381,"X좌표24":508.661,"X좌표23":571.227,"X좌표22":522.837,"X좌표21":512.063,"X좌표20":511.118,"Y좌표19":368.716,"Y좌표18":409.315}],"상의":[{}]},"라벨링":{"스타일":[{"스타일":"로맨틱"}],"아우터":[{}],"하의":[{}],"원피스":[{"기장":"미니","색상":"스카이블루","카테고리":"드레스","디테일":["러플","단추","리본","띠"],"소매기장":"민소매","소재":["실크"],"프린트":["무지"],"핏":"노멀"}],"상의":[{}]}},"파일 번호":107503,"파일 이름":"girlis_740_img.jpg"}}