{"이미지 정보":{"이미지 식별자":11180,"이미지 높이":800,"이미지 파일명":"dodream_050_14.jpg","이미지 너비":800},"데이터셋 정보":{"파일 생성일자":"2020-08-06 01:40:27","데이터셋 상세설명":{"렉트좌표":{"아우터":[{}],"하의":[{"X좌표":245.491,"Y좌표":102.364,"가로":293,"세로":250}],"원피스":[{}],"상의":[{}]},"폴리곤좌표":{"아우터":[{}],"하의":[{"Y좌표9":337.537,"Y좌표21":108.856,"Y좌표20":142.808,"X좌표19":283.938,"X좌표18":273.952,"X좌표17":245.991,"X좌표16":293.924,"X좌표15":335.866,"X좌표14":375.811,"X좌표13":389.791,"X좌표12":406.768,"X좌표11":458.695,"Y좌표4":102.864,"X좌표10":510.623,"Y좌표3":109.854,"Y좌표2":113.849,"Y좌표1":107.857,"Y좌표8":321.56,"Y좌표7":249.66,"Y좌표6":235.679,"Y좌표5":156.789,"Y좌표15":347.524,"Y좌표14":345.526,"X좌표8":539.583,"Y좌표17":328.55,"X좌표9":512.62,"Y좌표16":341.532,"Y좌표11":353.515,"Y좌표10":347.524,"Y좌표13":341.532,"Y좌표12":346.525,"X좌표2":379.805,"X좌표21":318.89,"X좌표3":423.744,"X좌표20":306.906,"X좌표1":317.891,"X좌표6":498.64,"Y좌표19":202.725,"X좌표7":503.633,"Y좌표18":253.654,"X좌표4":468.681,"X좌표5":485.658}],"원피스":[{}],"상의":[{}]},"라벨링":{"스타일":[{"스타일":"로맨틱","서브스타일":"스트리트"}],"아우터":[{}],"하의":[{"기장":"미니","색상":"핑크","카테고리":"스커트","디테일":["스티치","플레어"],"소재":["우븐"],"프린트":["무지"],"핏":"노멀"}],"원피스":[{}],"상의":[{}]}},"파일 번호":11180,"파일 이름":"dodream_050_14.jpg"}}