{"이미지 정보":{"이미지 식별자":113321,"이미지 높이":800,"이미지 파일명":"Mellisa_841_img.jpg","이미지 너비":800},"데이터셋 정보":{"파일 생성일자":"2020-08-10 09:47:49","데이터셋 상세설명":{"렉트좌표":{"아우터":[{}],"하의":[{}],"원피스":[{"X좌표":233.5,"Y좌표":13.5,"가로":360,"세로":779}],"상의":[{}]},"폴리곤좌표":{"아우터":[{}],"하의":[{}],"원피스":[{"Y좌표9":778.0,"X좌표19":425.0,"X좌표18":403.0,"X좌표17":365.0,"X좌표16":260.0,"X좌표15":247.0,"X좌표14":237.0,"X좌표13":268.0,"X좌표12":311.0,"X좌표11":322.0,"Y좌표4":305.0,"X좌표10":257.0,"Y좌표3":202.0,"Y좌표2":53.0,"Y좌표1":15.0,"Y좌표8":793.0,"Y좌표7":760.0,"Y좌표6":531.0,"Y좌표5":289.0,"Y좌표15":125.0,"Y좌표14":201.0,"X좌표8":416.0,"Y좌표17":14.0,"X좌표9":234.0,"Y좌표16":44.0,"Y좌표11":262.0,"Y좌표10":472.0,"Y좌표13":270.0,"Y좌표12":268.0,"X좌표2":534.0,"X좌표3":561.0,"X좌표1":424.0,"X좌표6":558.0,"Y좌표19":19.0,"X좌표7":594.0,"Y좌표18":87.0,"X좌표4":559.0,"X좌표5":516.0}],"상의":[{}]},"라벨링":{"스타일":[{"스타일":"로맨틱","서브스타일":"페미닌"}],"아우터":[{}],"하의":[{}],"원피스":[{"기장":"미디","색상":"핑크","서브색상":"레드","카테고리":"드레스","디테일":["프릴","플레어","셔링"],"소매기장":"7부소매","소재":["시폰"],"프린트":["플로럴"],"넥라인":"브이넥","핏":"노멀"}],"상의":[{}]}},"파일 번호":113321,"파일 이름":"Mellisa_841_img.jpg"}}