{"이미지 정보":{"이미지 식별자":521288,"이미지 높이":800,"이미지 파일명":"pt4911k04-600_5.jpg","이미지 너비":800},"데이터셋 정보":{"파일 생성일자":"2020-10-12 19:39:52","데이터셋 상세설명":{"렉트좌표":{"아우터":[{}],"하의":[{"X좌표":314.857,"Y좌표":240.172,"가로":198,"세로":170}],"원피스":[{}],"상의":[{"X좌표":276.909,"Y좌표":23.4736,"가로":235,"세로":222}]},"폴리곤좌표":{"아우터":[{}],"하의":[{"X좌표8":486.119,"X좌표9":514.08,"Y좌표9":388.467,"Y좌표11":242.669,"Y좌표10":240.672,"X좌표11":318.352,"X좌표2":329.337,"Y좌표4":408.439,"X좌표10":473.137,"X좌표3":315.357,"Y좌표3":396.456,"Y좌표2":336.539,"X좌표1":326.341,"Y좌표1":253.654,"X좌표6":410.225,"Y좌표8":409.437,"X좌표7":416.216,"Y좌표7":402.447,"X좌표4":324.344,"Y좌표6":378.481,"X좌표5":382.263,"Y좌표5":411.435}],"원피스":[{}],"상의":[{"Y좌표9":243.668,"X좌표19":348.311,"X좌표18":367.284,"X좌표17":420.211,"X좌표16":443.179,"X좌표15":468.144,"X좌표14":506.091,"X좌표13":513.081,"X좌표12":504.094,"X좌표11":459.156,"Y좌표4":150.797,"X좌표10":468.144,"Y좌표3":93.8764,"Y좌표2":45.943,"Y좌표1":26.9694,"Y좌표8":246.664,"Y좌표7":238.675,"Y좌표6":191.74,"Y좌표5":196.733,"Y좌표15":35.9569,"Y좌표14":63.918,"X좌표8":364.288,"Y좌표17":50.9361,"X좌표9":443.179,"Y좌표16":33.9597,"Y좌표11":196.733,"Y좌표10":225.693,"Y좌표13":132.822,"Y좌표12":193.737,"X좌표2":300.377,"X좌표3":277.409,"X좌표1":352.305,"X좌표6":314.358,"Y좌표19":23.9736,"X좌표7":323.345,"Y좌표18":40.95,"X좌표4":280.405,"X좌표5":292.388}]},"라벨링":{"스타일":[{"스타일":"리조트","서브스타일":"히피"}],"아우터":[{}],"하의":[{"기장":"미니","색상":"레드","서브색상":"화이트","카테고리":"팬츠","디테일":["포켓"],"소재":["우븐"],"프린트":["페이즐리"],"핏":"와이드"}],"원피스":[{}],"상의":[{"색상":"화이트","카테고리":"티셔츠","디테일":["드롭숄더"],"소매기장":"7부소매","소재":["저지"],"프린트":["무지"],"넥라인":"라운드넥","핏":"루즈"}]}},"파일 번호":521288,"파일 이름":"pt4911k04-600_5.jpg"}}